PexpectLibrary/__init__.py
PexpectLibrary/serialspawn.py
PexpectLibrary-0.2.0.dist-info/METADATA
PexpectLibrary-0.2.0.dist-info/WHEEL
PexpectLibrary-0.2.0.dist-info/top_level.txt
PexpectLibrary-0.2.0.dist-info/RECORD
